odoo/__init__.py
odoo/addons/__init__.py
odoo/addons/gate/__init__.py
odoo/addons/gate/__manifest__.py
odoo/addons/gate/controllers/__init__.py
odoo/addons/gate/controllers/main.py
odoo/addons/gate/models/__init__.py
odoo/addons/gate/models/things_basis.py
odoo/addons/gate/models/things_gate.py
odoo/addons/gate/models/things_route.py
odoo/addons/gate/wizard/__init__.py
odoo/addons/gate/wizard/gate_confirm_wizard.py
odoo12_addon_gate-12.0.1.0.3.dist-info/DESCRIPTION.rst
odoo12_addon_gate-12.0.1.0.3.dist-info/METADATA
odoo12_addon_gate-12.0.1.0.3.dist-info/RECORD
odoo12_addon_gate-12.0.1.0.3.dist-info/WHEEL
odoo12_addon_gate-12.0.1.0.3.dist-info/metadata.json
odoo12_addon_gate-12.0.1.0.3.dist-info/top_level.txt
