Metadata-Version: 2.0
Name: odoo12-addon-gate
Version: 12.0.1.0.3
Summary: Manage your Gateways and connect to your net of sensors and devices
Home-page: http://www.thingsintouch.com
Author: thingsintouch.com
License: AGPL-3
Platform: UNKNOWN
Classifier: Programming Language :: Python
Classifier: Framework :: Odoo
Classifier: License :: OSI Approved :: GNU Affero General Public License v3
Requires-Python: >=3.5
Requires-Dist: odoo (<12.1dev,>=12.0a)
